{
	"dynamic": [
		{
			"Items": ["573475fb24597737fb1379e1"],
			"Position":
			{
				"x": 38.836,
				"y": 5.363,
				"z": 41.331
			},
			"Rotation": 0,
			"id": "lootpoint (37)557280",
			"useGravity": true
		},
		{
			"Items": ["5734770f24597738025ee254"],
			"Position":
			{
				"x": 40.902,
				"y": 0.463,
				"z": -15.204
			},
			"Rotation": 0,
			"id": "lootpoint (57)557394",
			"useGravity": true
		},
		{
			"Items": ["57347c93245977448d35f6e3"],
			"Position":
			{
				"x": -19.82,
				"y": 3.786,
				"z": 28.326
			},
			"Rotation": 0,
			"id": "lootpoint (89)557540",
			"useGravity": true
		},
		{
			"Items": ["5c4eecc32e221602b412b440"],
			"Position":
			{
				"x": 12.028,
				"y": 8.483,
				"z": 39.751
			},
			"Rotation": 0,
			"id": "lootpoint (16)557566",
			"useGravity": true
		},
		{
			"Items": ["609b9e31506cf869cf3eaf41"],
			"Position":
			{
				"x": 33.142,
				"y": 2.674,
				"z": 15.958
			},
			"Rotation": 0,
			"id": "lootpoint (18)557614",
			"useGravity": true
		},
		{
			"Items": ["544fb25a4bdc2dfb738b4567"],
			"Position":
			{
				"x": 25.239,
				"y": 1.738,
				"z": 40.986
			},
			"Rotation": 0,
			"id": "loot_mix_food_med_ammo (52)558206",
			"randomRotation": true,
			"useGravity": true
		},
		{
			"Items": ["544fb45d4bdc2dee738b4568"],
			"Position":
			{
				"x": 25.318,
				"y": 2.16,
				"z": 35.148
			},
			"Rotation": 0,
			"id": "loot_mix_food_med_ammo (51)558238",
			"randomRotation": true,
			"useGravity": true
		},
		{
			"Items": ["5734773724597737fd047c14"],
			"Position":
			{
				"x": 31.025,
				"y": 8.903,
				"z": 41.063
			},
			"Rotation": 0,
			"id": "lootpoint (99)558386",
			"useGravity": true
		},
		{
			"Items": ["5e2af22086f7746d3f3c33fa"],
			"Position":
			{
				"x": -24.22,
				"y": 2.042,
				"z": 36.637
			},
			"Rotation": 0,
			"id": "lootpoint (81)558410",
			"useGravity": true
		},
		{
			"Items": ["59fafb5d86f774067a6f2084"],
			"Position":
			{
				"x": -15.59,
				"y": -3.613,
				"z": -30.395
			},
			"Rotation": 0,
			"id": "fuel1 (15)558490",
			"randomRotation": true,
			"useGravity": true
		},
		{
			"Items": ["59d64fc686f774171b243fe2"],
			"Position":
			{
				"x": 27.634,
				"y": 9.948,
				"z": 38.171
			},
			"Rotation": 0,
			"id": "lootpoint (100)558668",
			"useGravity": true
		},
		{
			"Items": ["57372e4a24597768553071c2", "56dff338d2720bbd668b4569"],
			"Position":
			{
				"x": 27.952,
				"y": 8.439,
				"z": 38.367
			},
			"Rotation": 0,
			"id": "lootpoint (73)558700",
			"useGravity": true
		},
		{
			"Items": ["590c5f0d86f77413997acfab"],
			"Position":
			{
				"x": 30.512,
				"y": 1.96,
				"z": 44.559
			},
			"Rotation": 0,
			"id": "food_drink1 (7)557164",
			"randomRotation": true,
			"useGravity": true
		},
		{
			"Items": ["573476d324597737da2adc13"],
			"Position":
			{
				"x": -24.091,
				"y": 8.971,
				"z": 52.265
			},
			"Rotation": 0,
			"id": "lootpoint557228",
			"useGravity": true
		},
		{
			"Items": ["57cffe20245977632f391a9d"],
			"Position":
			{
				"x": 42.933,
				"y": 0.704,
				"z": 30.049
			},
			"Rotation": 0,
			"id": "lootpoint (93)557402",
			"useGravity": true
		},
		{
			"Items": ["5d02778e86f774203e7dedbe"],
			"Position":
			{
				"x": -15.676,
				"y": 0.712,
				"z": -29.5
			},
			"Rotation": 0,
			"id": "meds (2)557450",
			"randomRotation": true,
			"useGravity": true
		},
		{
			"Items": ["5d1b31ce86f7742523398394"],
			"Position":
			{
				"x": 35.776,
				"y": 0.204,
				"z": -14.744
			},
			"Rotation": 0,
			"id": "tools1 (6)557458",
			"randomRotation": true,
			"useGravity": true
		},
		{
			"Items": ["58272d7f2459774f6311ddfd"],
			"Position":
			{
				"x": 23.496,
				"y": 8.955,
				"z": 36.062
			},
			"Rotation": 0,
			"id": "lootpoint (78)557558",
			"useGravity": true
		},
		{
			"Items": ["5751496424597720a27126da"],
			"Position":
			{
				"x": 15.971,
				"y": 0.268,
				"z": -20.553
			},
			"Rotation": 0,
			"id": "loot_mix_food_med_ammo (48)557590",
			"randomRotation": true,
			"useGravity": true
		},
		{
			"Items": ["5d1b3f2d86f774253763b735"],
			"Position":
			{
				"x": 39.544,
				"y": 0.332,
				"z": -14.472
			},
			"Rotation": 0,
			"id": "lootpoint (59)557598",
			"useGravity": true
		},
		{
			"Items": ["57372f5c24597769917c0131", "56dff4a2d2720bbd668b456a"],
			"Position":
			{
				"x": 25.255,
				"y": 1.629,
				"z": 35.382
			},
			"Rotation": 0,
			"id": "loot_mix_food_med_ammo (50)557710",
			"randomRotation": true,
			"useGravity": true
		},
		{
			"Items": ["591c4efa86f7741030027726"],
			"Position":
			{
				"x": 11.53,
				"y": 5.401,
				"z": 37.289
			},
			"Rotation": 0,
			"id": "lootpoint (83)557798",
			"useGravity": true
		},
		{
			"Items": ["5d1b317c86f7742523398392"],
			"Position":
			{
				"x": 31.243,
				"y": 4.845,
				"z": 38.986
			},
			"Rotation": 0,
			"id": "lootpoint (108)557806",
			"useGravity": true
		},
		{
			"Items": ["5673de654bdc2d180f8b456d"],
			"Position":
			{
				"x": 25.606,
				"y": 5.294,
				"z": 41.667
			},
			"Rotation": 0,
			"id": "lootpoint (112)557814",
			"useGravity": true
		},
		{
			"Items": ["544fb25a4bdc2dfb738b4567"],
			"Position":
			{
				"x": -15.815,
				"y": 0.517,
				"z": -24.691
			},
			"Rotation": 0,
			"id": "meds (7)557886",
			"randomRotation": true,
			"useGravity": true
		},
		{
			"Items": ["5d40412b86f7743cb332ac3a"],
			"Position":
			{
				"x": 5.132,
				"y": 8.105,
				"z": 57.96
			},
			"Rotation": 0,
			"id": "lootpoint (34)557950",
			"useGravity": true
		},
		{
			"Items": ["5751a25924597722c463c472"],
			"Position":
			{
				"x": 19.275,
				"y": 0.462,
				"z": -0.673
			},
			"Rotation": 0,
			"id": "lootpoint (94)557966",
			"useGravity": true
		},
		{
			"Items": ["590c2b4386f77425357b6123"],
			"Position":
			{
				"x": 14.529,
				"y": 9.391,
				"z": 34.633
			},
			"Rotation": 0,
			"id": "lootpoint (80)558222",
			"useGravity": true
		},
		{
			"Items": ["544fb3f34bdc2d03748b456a"],
			"Position":
			{
				"x": 46.348,
				"y": 0.77,
				"z": 31.643
			},
			"Rotation": 0,
			"id": "lootpoint (65)558296",
			"useGravity": true
		},
		{
			"Items": ["573476d324597737da2adc13"],
			"Position":
			{
				"x": 58.738,
				"y": 5.504,
				"z": 13.705
			},
			"Rotation": 0,
			"id": "lootpoint (39)558312",
			"useGravity": true
		},
		{
			"Items": ["544fb45d4bdc2dee738b4568"],
			"Position":
			{
				"x": 36.604,
				"y": 1.687,
				"z": 39.959
			},
			"Rotation": 0,
			"id": "loot_mix_food_med_ammo (58)558336",
			"randomRotation": true,
			"useGravity": true
		},
		{
			"Items": ["590c31c586f774245e3141b2"],
			"Position":
			{
				"x": -22.844,
				"y": 1.598,
				"z": 43.021
			},
			"Rotation": 0,
			"id": "lootpoint (91)558370",
			"useGravity": true
		},
		{
			"Items": ["57347c1124597737fb1379e3"],
			"Position":
			{
				"x": -21.208,
				"y": 1.6,
				"z": 55.25
			},
			"Rotation": 0,
			"id": "lootpoint (1)558586",
			"useGravity": true
		},
		{
			"Items": ["5755356824597772cb798962"],
			"Position":
			{
				"x": 33.45,
				"y": 5.264,
				"z": 40.29
			},
			"Rotation": 0,
			"id": "lootpoint (107)558602",
			"useGravity": true
		},
		{
			"Items": ["5d63d33b86f7746ea9275524"],
			"Position":
			{
				"x": 28.459,
				"y": -1.214,
				"z": -12.489
			},
			"Rotation": 0,
			"id": "tools1 (2)558644",
			"randomRotation": true,
			"useGravity": true
		},
		{
			"Items": ["57372e4a24597768553071c2", "56dff338d2720bbd668b4569"],
			"Position":
			{
				"x": 5.484,
				"y": 1.41,
				"z": -29.865
			},
			"Rotation": 0,
			"id": "loot_mix_food_med_ammo (59)558772",
			"randomRotation": true,
			"useGravity": true
		},
		{
			"Items": ["573476f124597737e04bf328"],
			"Position":
			{
				"x": -24.248,
				"y": 1.494,
				"z": 57.119
			},
			"Rotation": 0,
			"id": "lootpoint (5)557272",
			"useGravity": true
		},
		{
			"Items": ["573477e124597737dd42e191"],
			"Position":
			{
				"x": 6.023,
				"y": 1.498,
				"z": 0.539
			},
			"Rotation": 0,
			"id": "lootpoint (84)557312",
			"useGravity": true
		},
		{
			"Items": ["5751a25924597722c463c472"],
			"Position":
			{
				"x": -16.088,
				"y": 0.517,
				"z": -23.903
			},
			"Rotation": 0,
			"id": "meds (6)557410",
			"randomRotation": true,
			"useGravity": true
		},
		{
			"Items": ["573475fb24597737fb1379e1"],
			"Position":
			{
				"x": 5.73,
				"y": 2.378,
				"z": 55.629
			},
			"Rotation": 0,
			"id": "lootpoint (44)557434",
			"useGravity": true
		},
		{
			"Items": ["590c5a7286f7747884343aea"],
			"Position":
			{
				"x": -22.368,
				"y": 1.318,
				"z": 18.294
			},
			"Rotation": 0,
			"id": "lootpoint (86)557670",
			"useGravity": true
		},
		{
			"Items": ["5e2af29386f7746d4159f077"],
			"Position":
			{
				"x": 45.69,
				"y": 1.64,
				"z": 29.18
			},
			"Rotation": 0,
			"id": "lootpoint (41)557822",
			"useGravity": true
		},
		{
			"Items": ["5e2af00086f7746d3f3c33f7"],
			"Position":
			{
				"x": 28.206,
				"y": 1.73,
				"z": 40.09
			},
			"Rotation": 0,
			"id": "household557870",
			"randomRotation": true,
			"useGravity": true
		},
		{
			"Items": ["5d235a5986f77443f6329bc6"],
			"Position":
			{
				"x": 23.161,
				"y": 9.186,
				"z": 36.063
			},
			"Rotation": 0,
			"id": "lootpoint (76)558190",
			"useGravity": true
		},
		{
			"Items": ["57347b8b24597737dd42e192"],
			"Position":
			{
				"x": 34.234,
				"y": 1.19,
				"z": 33.684
			},
			"Rotation": 0,
			"id": "lootpoint (68)558402",
			"useGravity": true
		},
		{
			"Items": ["5e8488fa988a8701445df1e4"],
			"Position":
			{
				"x": -14.105,
				"y": 1.49,
				"z": -14.445
			},
			"Rotation": 0,
			"id": "meds (10)558418",
			"randomRotation": true,
			"useGravity": true
		},
		{
			"Items": ["5672cb124bdc2d1a0f8b4568"],
			"Position":
			{
				"x": 27.799,
				"y": 0.734,
				"z": 17.162
			},
			"Rotation": 0,
			"id": "lootpoint (33)558466",
			"useGravity": true
		},
		{
			"Items": ["57372ac324597767001bc261", "56dfef82d2720bbd668b4567"],
			"Position":
			{
				"x": 1.968,
				"y": -3.717,
				"z": -25.995
			},
			"Rotation": 0,
			"id": "ammo1 (6)558562",
			"randomRotation": true,
			"useGravity": true
		},
		{
			"Items": ["59e35cbb86f7741778269d83"],
			"Position":
			{
				"x": 27.872,
				"y": 5.293,
				"z": 42.138
			},
			"Rotation": 0,
			"id": "lootpoint (113)557328",
			"useGravity": true
		},
		{
			"Items": ["574d967124597745970e7c94", "574dad8024597745964bf05c", "574db213245977459a2f3f5d", "587df3a12459772c28142567", "5656d7c34bdc2d9d198b4587"],
			"Position":
			{
				"x": 27.655,
				"y": 9.405,
				"z": 37.498
			},
			"Rotation": 0,
			"id": "lootpoint (102)557352",
			"useGravity": true
		},
		{
			"Items": ["590c678286f77426c9660122"],
			"Position":
			{
				"x": -19.837,
				"y": 0.733,
				"z": -25.825
			},
			"Rotation": 0,
			"id": "meds (5)557694",
			"randomRotation": true,
			"useGravity": true
		},
		{
			"Items": ["56742c284bdc2d98058b456d"],
			"Position":
			{
				"x": -11.532,
				"y": 2.401,
				"z": 56.054
			},
			"Rotation": 0,
			"id": "lootpoint (120)557918",
			"useGravity": true
		},
		{
			"Items": ["57513f9324597720a7128161"],
			"Position":
			{
				"x": 36.069,
				"y": 0.91,
				"z": -9.636
			},
			"Rotation": 0,
			"id": "food_drink1 (2)558058",
			"randomRotation": true,
			"useGravity": true
		},
		{
			"Items": ["590a3b0486f7743954552bdb"],
			"Position":
			{
				"x": 21.717,
				"y": 9.106,
				"z": 39.973
			},
			"Rotation": 0,
			"id": "lootpoint (49)558214",
			"useGravity": true
		},
		{
			"Items": ["590c2b4386f77425357b6123"],
			"Position":
			{
				"x": 40.915,
				"y": 0.43,
				"z": -9.394
			},
			"Rotation": 0,
			"id": "lootpoint (56)558684",
			"useGravity": true
		},
		{
			"Items": ["59e7635f86f7742cbf2c1095"],
			"Position":
			{
				"x": 12.32283,
				"y": 8.427,
				"z": 36.9212646
			},
			"Rotation":
			{
				"x": 271.255371,
				"y": 0.000194819455,
				"z": 22.6169052
			},
			"id": "Loot_armor_low (5)557252"
		},
		{
			"Items": ["57347c1124597737fb1379e3"],
			"Position":
			{
				"x": 3.105,
				"y": -3.628,
				"z": -11.622
			},
			"Rotation": 0,
			"id": "loot_shelter_electr (8)557426",
			"randomRotation": true,
			"useGravity": true
		},
		{
			"Items": ["5751a25924597722c463c472"],
			"Position":
			{
				"x": -19.648,
				"y": 0.816,
				"z": -25.03
			},
			"Rotation": 0,
			"id": "meds (9)557734",
			"randomRotation": true,
			"useGravity": true
		},
		{
			"Items": ["5e2aef7986f7746d3f3c33f5"],
			"Position":
			{
				"x": 27.084,
				"y": 1.89,
				"z": 38.833
			},
			"Rotation": 0,
			"id": "household558074",
			"randomRotation": true,
			"useGravity": true
		},
		{
			"Items": ["5d1b317c86f7742523398392"],
			"Position":
			{
				"x": 36.702,
				"y": 0.73,
				"z": -14.923
			},
			"Rotation": 0,
			"id": "tools1 (9)558090",
			"randomRotation": true,
			"useGravity": true
		},
		{
			"Items": ["5d40425986f7743185265461"],
			"Position":
			{
				"x": 36.033,
				"y": 0.204,
				"z": -14.442
			},
			"Rotation": 0,
			"id": "tools1 (8)557172",
			"randomRotation": true,
			"useGravity": true
		},
		{
			"Items": ["5d40407c86f774318526545a"],
			"Position":
			{
				"x": 23.458,
				"y": 1.81,
				"z": 35.05
			},
			"Rotation": 0,
			"id": "loot_mix_food_med_ammo (46)557188",
			"randomRotation": true,
			"useGravity": true
		},
		{
			"Items": ["5737339e2459776af261abeb", "56dff216d2720bbd668b4568"],
			"Position":
			{
				"x": 2.681,
				"y": -3.089,
				"z": -28.43
			},
			"Rotation": 0,
			"id": "ammo1 (11)557260",
			"randomRotation": true,
			"useGravity": true
		},
		{
			"Items": ["590a3cd386f77436f20848cb"],
			"Position":
			{
				"x": 26.762,
				"y": 1.843,
				"z": 42.622
			},
			"Rotation": 0,
			"id": "electr1 (1)557524",
			"randomRotation": true,
			"useGravity": true
		},
		{
			"Items": ["5672cb304bdc2dc2088b456a"],
			"Position":
			{
				"x": 57.026,
				"y": 1.353,
				"z": 20.07
			},
			"Rotation": 0,
			"id": "lootpoint (43)557606",
			"useGravity": true
		},
		{
			"Items": ["5d1b31ce86f7742523398394"],
			"Position":
			{
				"x": 36.548,
				"y": 0.967,
				"z": -11.019
			},
			"Rotation": 0,
			"id": "tools1 (4)557782",
			"randomRotation": true,
			"useGravity": true
		},
		{
			"Items": ["5af04b6486f774195a3ebb49"],
			"Position":
			{
				"x": 27.848,
				"y": -1.214,
				"z": -11.977
			},
			"Rotation": 0,
			"id": "tools1 (1)557854",
			"randomRotation": true,
			"useGravity": true
		},
		{
			"Items": ["59e3596386f774176c10a2a2"],
			"Position":
			{
				"x": -8.161,
				"y": 1.847,
				"z": 30.663
			},
			"Rotation": 0,
			"id": "lootpoint (88)557910",
			"useGravity": true
		},
		{
			"Items": ["573476d324597737da2adc13"],
			"Position":
			{
				"x": 32.568,
				"y": 4.873,
				"z": 47.73
			},
			"Rotation": 0,
			"id": "lootpoint (115)557986",
			"useGravity": true
		},
		{
			"Items": ["59e35ef086f7741777737012"],
			"Position":
			{
				"x": -23.099,
				"y": 2.262,
				"z": 53.573
			},
			"Rotation": 0,
			"id": "lootpoint (45)558158",
			"useGravity": true
		},
		{
			"Items": ["573476f124597737e04bf328"],
			"Position":
			{
				"x": 40.65,
				"y": 0.525,
				"z": -10.365
			},
			"Rotation": 0,
			"id": "lootpoint (58)558230",
			"useGravity": true
		},
		{
			"Items": ["5751a25924597722c463c472"],
			"Position":
			{
				"x": 27.997,
				"y": 5.237,
				"z": 46.734
			},
			"Rotation": 0,
			"id": "lootpoint (116)558264",
			"useGravity": true
		},
		{
			"Items": ["57347c5b245977448d35f6e1"],
			"Position":
			{
				"x": 40.179,
				"y": 1.065,
				"z": -15.429
			},
			"Rotation": 0,
			"id": "lootpoint (106)558628",
			"useGravity": true
		},
		{
			"Items": ["544fb62a4bdc2dfb738b4568"],
			"Position":
			{
				"x": 64.961,
				"y": 1.028,
				"z": -36.884
			},
			"Rotation": 0,
			"id": "loot_mix_food_med_ammo (63)558676",
			"randomRotation": true,
			"useGravity": true
		}
	],
	"forced": [
		{
			"Items": ["591093bb86f7747caa7bb2ee"],
			"Position":
			{
				"x": -18.8457,
				"y": 0.6842,
				"z": 21.6351
			},
			"Rotation":
			{
				"x": 338.5508,
				"y": 18.11368,
				"z": 80.9849548
			},
			"id": "loot_quest_letter557344"
		},
		{
			"Items": ["593a87af86f774122f54a951"],
			"Position":
			{
				"x": 26.3819,
				"y": 9.1867,
				"z": 38.9887
			},
			"Rotation":
			{
				"x": 272.994354,
				"y": 134.752258,
				"z": 270.002625
			},
			"id": "loot_quest_r557846"
		}
	],
	"mounted": [],
	"static": [
		{
			"IsStatic": true,
			"Items": [
				{
					"_id": "618940532ec84622b635b0b3",
					"_tpl": "578f8778245977358849a9b5"
				}
			],
			"Position": 0,
			"Rotation": 0,
			"id": "00171",
			"useGravity": true
		},
		{
			"IsStatic": true,
			"Items": [
				{
					"_id": "618940532ec84622b635b0b4",
					"_tpl": "5d6fd45b86f774317075ed43"
				}
			],
			"Position": 0,
			"Rotation": 0,
			"id": "00185",
			"useGravity": true
		},
		{
			"IsStatic": true,
			"Items": [
				{
					"_id": "618940532ec84622b635b0b8",
					"_tpl": "5909d5ef86f77467974efbd8"
				}
			],
			"Position": 0,
			"Rotation": 0,
			"id": "00147",
			"useGravity": true
		},
		{
			"IsStatic": true,
			"Items": [
				{
					"_id": "618940532ec84622b635b0bc",
					"_tpl": "5909d5ef86f77467974efbd8"
				}
			],
			"Position": 0,
			"Rotation": 0,
			"id": "00182",
			"useGravity": true
		},
		{
			"IsStatic": true,
			"Items": [
				{
					"_id": "618940532ec84622b635b0bd",
					"_tpl": "578f87ad245977356274f2cc"
				}
			],
			"Position": 0,
			"Rotation": 0,
			"id": "00158",
			"useGravity": true
		},
		{
			"IsStatic": true,
			"Items": [
				{
					"_id": "618940532ec84622b635b0bf",
					"_tpl": "578f87ad245977356274f2cc"
				}
			],
			"Position": 0,
			"Rotation": 0,
			"id": "00157",
			"useGravity": true
		},
		{
			"IsStatic": true,
			"Items": [
				{
					"_id": "618940532ec84622b635b0c0",
					"_tpl": "578f8778245977358849a9b5"
				}
			],
			"Position": 0,
			"Rotation": 0,
			"id": "00173",
			"useGravity": true
		},
		{
			"IsStatic": true,
			"Items": [
				{
					"_id": "618940532ec84622b635b0c3",
					"_tpl": "578f87ad245977356274f2cc"
				}
			],
			"Position": 0,
			"Rotation": 0,
			"id": "00156",
			"useGravity": true
		},
		{
			"IsStatic": true,
			"Items": [
				{
					"_id": "618940532ec84622b635b0c4",
					"_tpl": "578f87ad245977356274f2cc"
				}
			],
			"Position": 0,
			"Rotation": 0,
			"id": "00184",
			"useGravity": true
		},
		{
			"IsStatic": true,
			"Items": [
				{
					"_id": "618940532ec84622b635b0c7",
					"_tpl": "5d6fe50986f77449d97f7463"
				}
			],
			"Position": 0,
			"Rotation": 0,
			"id": "00186",
			"useGravity": true
		},
		{
			"IsStatic": true,
			"Items": [
				{
					"_id": "618940532ec84622b635b0cb",
					"_tpl": "578f87ad245977356274f2cc"
				}
			],
			"Position": 0,
			"Rotation": 0,
			"id": "00155",
			"useGravity": true
		},
		{
			"IsStatic": true,
			"Items": [
				{
					"_id": "618940532ec84622b635b0ce",
					"_tpl": "578f87ad245977356274f2cc"
				}
			],
			"Position": 0,
			"Rotation": 0,
			"id": "00154",
			"useGravity": true
		},
		{
			"IsStatic": true,
			"Items": [
				{
					"_id": "618940532ec84622b635b0d0",
					"_tpl": "578f8782245977354405a1e3"
				}
			],
			"Position": 0,
			"Rotation": 0,
			"id": "00160",
			"useGravity": true
		},
		{
			"IsStatic": true,
			"Items": [
				{
					"_id": "618940532ec84622b635b0d4",
					"_tpl": "578f87b7245977356274f2cd"
				}
			],
			"Position": 0,
			"Rotation": 0,
			"id": "00164",
			"useGravity": true
		},
		{
			"IsStatic": true,
			"Items": [
				{
					"_id": "618940532ec84622b635b0d5",
					"_tpl": "578f87b7245977356274f2cd"
				}
			],
			"Position": 0,
			"Rotation": 0,
			"id": "00163",
			"useGravity": true
		},
		{
			"IsStatic": true,
			"Items": [
				{
					"_id": "618940532ec84622b635b0d7",
					"_tpl": "578f87b7245977356274f2cd"
				}
			],
			"Position": 0,
			"Rotation": 0,
			"id": "00162",
			"useGravity": true
		},
		{
			"IsStatic": true,
			"Items": [
				{
					"_id": "618940532ec84622b635b0da",
					"_tpl": "578f87b7245977356274f2cd"
				}
			],
			"Position": 0,
			"Rotation": 0,
			"id": "00161",
			"useGravity": true
		},
		{
			"IsStatic": true,
			"Items": [
				{
					"_id": "618940532ec84622b635b0dc",
					"_tpl": "578f87ad245977356274f2cc"
				}
			],
			"Position": 0,
			"Rotation": 0,
			"id": "00153",
			"useGravity": true
		},
		{
			"IsStatic": true,
			"Items": [
				{
					"_id": "618940532ec84622b635b0de",
					"_tpl": "5909d5ef86f77467974efbd8"
				}
			],
			"Position": 0,
			"Rotation": 0,
			"id": "00145",
			"useGravity": true
		},
		{
			"IsStatic": true,
			"Items": [
				{
					"_id": "618940532ec84622b635b0e0",
					"_tpl": "5909d50c86f774659e6aaebe"
				}
			],
			"Position": 0,
			"Rotation": 0,
			"id": "00183",
			"useGravity": true
		},
		{
			"IsStatic": true,
			"Items": [
				{
					"_id": "618940532ec84622b635b0e1",
					"_tpl": "5909d50c86f774659e6aaebe"
				}
			],
			"Position": 0,
			"Rotation": 0,
			"id": "00178",
			"useGravity": true
		},
		{
			"IsStatic": true,
			"Items": [
				{
					"_id": "618940532ec84622b635b0e4",
					"_tpl": "578f87ad245977356274f2cc"
				}
			],
			"Position": 0,
			"Rotation": 0,
			"id": "00159",
			"useGravity": true
		},
		{
			"IsStatic": true,
			"Items": [
				{
					"_id": "618940532ec84622b635b0e5",
					"_tpl": "578f87ad245977356274f2cc"
				}
			],
			"Position": 0,
			"Rotation": 0,
			"id": "00187",
			"useGravity": true
		},
		{
			"IsStatic": true,
			"Items": [
				{
					"_id": "618940532ec84622b635b0f0",
					"_tpl": "5909d36d86f774660f0bb900"
				}
			],
			"Position": 0,
			"Rotation": 0,
			"id": "00188",
			"useGravity": true
		},
		{
			"IsStatic": true,
			"Items": [
				{
					"_id": "618940532ec84622b635b0f2",
					"_tpl": "578f87ad245977356274f2cc"
				}
			],
			"Position": 0,
			"Rotation": 0,
			"id": "00152",
			"useGravity": true
		},
		{
			"IsStatic": true,
			"Items": [
				{
					"_id": "618940532ec84622b635b0f4",
					"_tpl": "578f8778245977358849a9b5"
				}
			],
			"Position": 0,
			"Rotation": 0,
			"id": "00176",
			"useGravity": true
		},
		{
			"IsStatic": true,
			"Items": [
				{
					"_id": "618940532ec84622b635b0f6",
					"_tpl": "578f8778245977358849a9b5"
				}
			],
			"Position": 0,
			"Rotation": 0,
			"id": "00174",
			"useGravity": true
		},
		{
			"IsStatic": true,
			"Items": [
				{
					"_id": "618940532ec84622b635b0f9",
					"_tpl": "578f87ad245977356274f2cc"
				}
			],
			"Position": 0,
			"Rotation": 0,
			"id": "00151",
			"useGravity": true
		},
		{
			"IsStatic": true,
			"Items": [
				{
					"_id": "618940532ec84622b635b104",
					"_tpl": "578f87a3245977356274f2cb"
				}
			],
			"Position": 0,
			"Rotation": 0,
			"id": "00181",
			"useGravity": true
		},
		{
			"IsStatic": true,
			"Items": [
				{
					"_id": "618940532ec84622b635b106",
					"_tpl": "578f8778245977358849a9b5"
				}
			],
			"Position": 0,
			"Rotation": 0,
			"id": "00170",
			"useGravity": true
		},
		{
			"IsStatic": true,
			"Items": [
				{
					"_id": "618940532ec84622b635b108",
					"_tpl": "578f87ad245977356274f2cc"
				}
			],
			"Position": 0,
			"Rotation": 0,
			"id": "00180",
			"useGravity": true
		},
		{
			"IsStatic": true,
			"Items": [
				{
					"_id": "618940532ec84622b635b109",
					"_tpl": "578f87ad245977356274f2cc"
				}
			],
			"Position": 0,
			"Rotation": 0,
			"id": "00150",
			"useGravity": true
		},
		{
			"IsStatic": true,
			"Items": [
				{
					"_id": "618940532ec84622b635b10a",
					"_tpl": "5909d76c86f77471e53d2adf"
				}
			],
			"Position": 0,
			"Rotation": 0,
			"id": "00148",
			"useGravity": true
		},
		{
			"IsStatic": true,
			"Items": [
				{
					"_id": "618940532ec84622b635b10c",
					"_tpl": "578f87ad245977356274f2cc"
				}
			],
			"Position": 0,
			"Rotation": 0,
			"id": "00149",
			"useGravity": true
		},
		{
			"IsStatic": true,
			"Items": [
				{
					"_id": "618940532ec84622b635b10e",
					"_tpl": "5909e4b686f7747f5b744fa4"
				}
			],
			"Position": 0,
			"Rotation": 0,
			"id": "00175",
			"useGravity": true
		},
		{
			"IsStatic": true,
			"Items": [
				{
					"_id": "618940532ec84622b635b112",
					"_tpl": "5909d24f86f77466f56e6855"
				}
			],
			"Position": 0,
			"Rotation": 0,
			"id": "00179",
			"useGravity": true
		},
		{
			"IsStatic": true,
			"Items": [
				{
					"_id": "618940532ec84622b635b116",
					"_tpl": "5909d5ef86f77467974efbd8"
				}
			],
			"Position": 0,
			"Rotation": 0,
			"id": "00146",
			"useGravity": true
		},
		{
			"IsStatic": true,
			"Items": [
				{
					"_id": "618940532ec84622b635b118",
					"_tpl": "578f8778245977358849a9b5"
				}
			],
			"Position": 0,
			"Rotation": 0,
			"id": "00169",
			"useGravity": true
		},
		{
			"IsStatic": true,
			"Items": [
				{
					"_id": "618940532ec84622b635b11b",
					"_tpl": "578f8778245977358849a9b5"
				}
			],
			"Position": 0,
			"Rotation": 0,
			"id": "00172",
			"useGravity": true
		},
		{
			"IsStatic": true,
			"Items": [
				{
					"_id": "618940532ec84622b635b11d",
					"_tpl": "578f87b7245977356274f2cd"
				}
			],
			"Position": 0,
			"Rotation": 0,
			"id": "00168",
			"useGravity": true
		},
		{
			"IsStatic": true,
			"Items": [
				{
					"_id": "618940532ec84622b635b11f",
					"_tpl": "578f87b7245977356274f2cd"
				}
			],
			"Position": 0,
			"Rotation": 0,
			"id": "00167",
			"useGravity": true
		},
		{
			"IsStatic": true,
			"Items": [
				{
					"_id": "618940532ec84622b635b122",
					"_tpl": "578f87b7245977356274f2cd"
				}
			],
			"Position": 0,
			"Rotation": 0,
			"id": "00166",
			"useGravity": true
		},
		{
			"IsStatic": true,
			"Items": [
				{
					"_id": "618940532ec84622b635b125",
					"_tpl": "578f87b7245977356274f2cd"
				}
			],
			"Position": 0,
			"Rotation": 0,
			"id": "00165",
			"useGravity": true
		},
		{
			"IsStatic": true,
			"Items": [
				{
					"_id": "618940532ec84622b635b126",
					"_tpl": "578f8778245977358849a9b5"
				}
			],
			"Position": 0,
			"Rotation": 0,
			"id": "00189",
			"useGravity": true
		},
		{
			"IsStatic": true,
			"Items": [
				{
					"_id": "618940532ec84622b635b128",
					"_tpl": "578f8778245977358849a9b5"
				}
			],
			"Position": 0,
			"Rotation": 0,
			"id": "00190",
			"useGravity": true
		}
	]
}
